README.md
setup.py
bfxapi/__init__.py
bfxapi/client.py
bfxapi/version.py
bfxapi/models/__init__.py
bfxapi/models/deposit_address.py
bfxapi/models/funding_credit.py
bfxapi/models/funding_loan.py
bfxapi/models/funding_offer.py
bfxapi/models/funding_ticker.py
bfxapi/models/ledger.py
bfxapi/models/notification.py
bfxapi/models/order.py
bfxapi/models/order_book.py
bfxapi/models/position.py
bfxapi/models/subscription.py
bfxapi/models/ticker.py
bfxapi/models/trade.py
bfxapi/models/transfer.py
bfxapi/models/wallet.py
bfxapi/models/withdraw.py
bfxapi/rest/__init__.py
bfxapi/rest/bfx_rest.py
bfxapi/tests/__init__.py
bfxapi/tests/helpers.py
bfxapi/tests/test_decimal.py
bfxapi/tests/test_ws_capacity.py
bfxapi/tests/test_ws_orderbook.py
bfxapi/tests/test_ws_orders.py
bfxapi/tests/test_ws_subscriptions.py
bfxapi/utils/__init__.py
bfxapi/utils/auth.py
bfxapi/utils/custom_logger.py
bfxapi/utils/decimal.py
bfxapi/utils/testing_tools.py
bfxapi/websockets/__init__.py
bfxapi/websockets/bfx_websocket.py
bfxapi/websockets/generic_websocket.py
bfxapi/websockets/order_manager.py
bfxapi/websockets/subscription_manager.py
bfxapi/websockets/wallet_manager.py
bitfinex_py_api.egg-info/PKG-INFO
bitfinex_py_api.egg-info/SOURCES.txt
bitfinex_py_api.egg-info/dependency_links.txt
bitfinex_py_api.egg-info/requires.txt
bitfinex_py_api.egg-info/top_level.txt