Metadata-Version: 2.1
Name: bitfinex-py-api
Version: 1.0.0
Summary: Bitfinex Python API
Home-page: https://github.com/bitfinexcom/bitfinex-api-py
Author: Bitfinex
Author-email: support@bitfinex.com
License: UNKNOWN
Project-URL: Bug Reports, https://github.com/bitfinexcom/bitfinex-api-py/issues
Project-URL: Source, https://github.com/bitfinexcom/bitfinex-api-py
Keywords: uggel,bitfinex,api,trading
Platform: UNKNOWN
Classifier: Development Status :: 5 - Production/Stable
Classifier: Intended Audience :: Developers
Classifier: Topic :: Software Development :: Build Tools
Classifier: License :: OSI Approved :: Apache Software License
Classifier: Programming Language :: Python :: 3.0
Classifier: Programming Language :: Python :: 3.2
Classifier: Programming Language :: Python :: 3.3
Classifier: Programming Language :: Python :: 3.4
Classifier: Programming Language :: Python :: 3.5
Classifier: Programming Language :: Python :: 3.6
Classifier: Programming Language :: Python :: 3.7
Requires-Python: >=3.0.0, <4
